LICENSE
README.md
tfs/__init__.py
tfs/connection.py
tfs/resources.py
dohq_tfs-1.1.1.dist-info/LICENSE
dohq_tfs-1.1.1.dist-info/METADATA
dohq_tfs-1.1.1.dist-info/WHEEL
dohq_tfs-1.1.1.dist-info/top_level.txt
dohq_tfs-1.1.1.dist-info/zip-safe
dohq_tfs-1.1.1.dist-info/RECORD
